MANIFEST.in
Pipfile
README.md
setup.py
src/django_base_project/__init__.py
src/django_base_project/manage.py
src/django_base_project.egg-info/PKG-INFO
src/django_base_project.egg-info/SOURCES.txt
src/django_base_project.egg-info/dependency_links.txt
src/django_base_project.egg-info/requires.txt
src/django_base_project.egg-info/top_level.txt
src/django_base_project/webapp/__init__.py
src/django_base_project/webapp/settings.py
src/django_base_project/webapp/urls.py
src/django_base_project/webapp/wsgi.py