Metadata-Version: 2.1
Name: django-base-project
Version: 0.0.6
Summary: A base django project containing commonly used functionality
Home-page: https://github.com/jonathanmeier5/base-django-project
Author: Jonathan Meier
Author-email: jonathan.w.meier@gmail.com
License: UNKNOWN
Platform: UNKNOWN
Classifier: Programming Language :: Python :: 3
Classifier: License :: OSI Approved :: MIT License
Classifier: Operating System :: OS Independent
